[
  {
    "title": "Egyptian Pyramids",
    "description": "Cairo, 1920, an archaeologist is about to discover the secret of the Egyptian Pyramids...",
    "videoUrl": "https://storage.cloud.google.com/amezon-2-a89b2.appspot.com/videos/The%20Egyptian%20Pyramids.mp4",
    "thumbnailUrl": "https://i.ytimg.com/an_webp/j6PbonHsqW0/mqdefault_6s.webp?du=3000&sqp=CMyS7qEG&rs=AOn4CLBZx4lUne3dAJR2ZU1sYQ5ghNs9jg",
    "genre": "Comedy",
    "duration": "3 minutes"
  },
  {
    "title": "Funny birds",
    "description": "Poor little birds, but it was their own fault for laughing at the giant bird! 💚 Nonetheless, it was still hilarious to watch! 💚",
    "videoUrl": "https://storage.cloud.google.com/amezon-2-a89b2.appspot.com/videos/Funny%20Birds.mp4",
    "thumbnailUrl": "https://i.ytimg.com/vi/lK13SW0QW04/hq720.jpg?sqp=-…RhGIE0oZTAP&rs=AOn4CLCyxO0uTOPnrRsgaR6l9BcnRO79Xg",
    "genre": "Comedy",
    "duration": "4 minutes"
  },
  {
    "title": "piper-atittude",
    "description": "life teaches so many lessons.in this story,explains a Newbie bird how struggles and learn how to overcome from it.",
    "videoUrl": "https://storage.cloud.google.com/amezon-2-a89b2.appspot.com/videos/Piper%20-%20Atitude.mp4",
    "thumbnailUrl": "https://i.ytimg.com/vi/m8q8M50cF5E/hq720.jpg?sqp=-…RhlIFQoSzAP&rs=AOn4CLCw6GIjeychfi2zxKbflBO1TsigWg",
    "genre": "Motivation",
    "duration": "7 minutes"
  },
  {
    "title": "Planet Unknown",
    "description": "At the end of 21st century, mankind was facing global resource depletion. Space Rovers were sent out to find potential inhabitable planets.",
    "videoUrl": "https://storage.cloud.google.com/amezon-2-a89b2.appspot.com/videos/Planet%20Unknown.mp4",
    "thumbnailUrl": "https://i.ytimg.com/vi/nTpR1QayngU/hq720.jpg?sqp=-…AFwAcABBg==&rs=AOn4CLBxf1xajRpAd4S4sfpd6QrPl94qwA",
    "genre": "Sci-Fi",
    "duration": "10 minutes"
  }
]
